{"interfaceLanguages":{"swift":[{"children":[{"title":"Essentials","type":"groupMarker"},{"path":"\/documentation\/paywall\/ecosystem","title":"Understanding How Superwall Works","type":"article"},{"children":[{"title":"The Delegate","type":"groupMarker"},{"children":[{"title":"Required Methods","type":"groupMarker"},{"path":"\/documentation\/paywall\/paywalldelegate\/purchase(product:)","title":"func purchase(product: SKProduct)","type":"method"},{"path":"\/documentation\/paywall\/paywalldelegate\/restorepurchases(completion:)","title":"func restorePurchases(completion: (Bool) -> Void)","type":"method"},{"path":"\/documentation\/paywall\/paywalldelegate\/isusersubscribed()","title":"func isUserSubscribed() -> Bool","type":"method"},{"title":"Optional Methods","type":"groupMarker"},{"path":"\/documentation\/paywall\/paywalldelegate\/trackanalyticsevent(withname:params:)","title":"func trackAnalyticsEvent(withName: String, params: [String : Any])","type":"method"},{"path":"\/documentation\/paywall\/paywalldelegate\/handlecustompaywallaction(withname:)","title":"func handleCustomPaywallAction(withName: String)","type":"method"},{"path":"\/documentation\/paywall\/paywalldelegate\/handlelog(level:scope:message:info:error:)","title":"func handleLog(level: String, scope: String, message: String?, info: [String : Any]?, error: Swift.Error?)","type":"method"},{"path":"\/documentation\/paywall\/paywalldelegate\/willdismisspaywall()","title":"func willDismissPaywall()","type":"method"},{"path":"\/documentation\/paywall\/paywalldelegate\/diddismisspaywall()","title":"func didDismissPaywall()","type":"method"},{"path":"\/documentation\/paywall\/paywalldelegate\/willpresentpaywall()","title":"func willPresentPaywall()","type":"method"},{"path":"\/documentation\/paywall\/paywalldelegate\/didpresentpaywall()","title":"func didPresentPaywall()","type":"method"},{"path":"\/documentation\/paywall\/paywalldelegate\/willopendeeplink(url:)","title":"func willOpenDeepLink(url: URL)","type":"method"},{"path":"\/documentation\/paywall\/paywalldelegate\/willopenurl(url:)","title":"func willOpenURL(url: URL)","type":"method"}],"path":"\/documentation\/paywall\/paywalldelegate","title":"PaywallDelegate","type":"protocol"},{"path":"\/documentation\/paywall\/custompaywallbuttons","title":"Custom Paywall Buttons","type":"article"},{"path":"\/documentation\/paywall\/thirdpartyanalytics","title":"Third-Party Analytics","type":"article"},{"title":"Setting the Paywall Options","type":"groupMarker"},{"children":[{"title":"Structures","type":"groupMarker"},{"children":[{"title":"Instance Properties","type":"groupMarker"},{"path":"\/documentation\/paywall\/paywalloptions\/logging-swift.struct\/level","title":"var level: LogLevel?","type":"property"},{"path":"\/documentation\/paywall\/paywalloptions\/logging-swift.struct\/scopes","title":"var scopes: Set<LogScope>","type":"property"}],"path":"\/documentation\/paywall\/paywalloptions\/logging-swift.struct","title":"PaywallOptions.Logging","type":"struct"},{"children":[{"title":"Instance Properties","type":"groupMarker"},{"path":"\/documentation\/paywall\/paywalloptions\/restorefailed-swift.struct\/closebuttontitle","title":"var closeButtonTitle: String","type":"property"},{"path":"\/documentation\/paywall\/paywalloptions\/restorefailed-swift.struct\/message","title":"var message: String","type":"property"},{"path":"\/documentation\/paywall\/paywalloptions\/restorefailed-swift.struct\/title","title":"var title: String","type":"property"}],"path":"\/documentation\/paywall\/paywalloptions\/restorefailed-swift.struct","title":"PaywallOptions.RestoreFailed","type":"struct"},{"title":"Instance Properties","type":"groupMarker"},{"path":"\/documentation\/paywall\/paywalloptions\/automaticallydismiss","title":"var automaticallyDismiss: Bool","type":"property"},{"path":"\/documentation\/paywall\/paywalloptions\/isexternaldatacollectionenabled","title":"var isExternalDataCollectionEnabled: Bool","type":"property"},{"path":"\/documentation\/paywall\/paywalloptions\/isgamecontrollerenabled","title":"var isGameControllerEnabled: Bool","type":"property"},{"path":"\/documentation\/paywall\/paywalloptions\/ishapticfeedbackenabled","title":"var isHapticFeedbackEnabled: Bool","type":"property"},{"path":"\/documentation\/paywall\/paywalloptions\/logging-swift.property","title":"var logging: PaywallOptions.Logging","type":"property"},{"path":"\/documentation\/paywall\/paywalloptions\/networkenvironment","title":"var networkEnvironment: PaywallNetworkEnvironment","type":"property"},{"path":"\/documentation\/paywall\/paywalloptions\/restorefailed-swift.property","title":"var restoreFailed: PaywallOptions.RestoreFailed","type":"property"},{"path":"\/documentation\/paywall\/paywalloptions\/shouldpreloadpaywalls","title":"var shouldPreloadPaywalls: Bool","type":"property"},{"path":"\/documentation\/paywall\/paywalloptions\/transactionbackgroundview-swift.property","title":"var transactionBackgroundView: TransactionBackgroundView?","type":"property"},{"title":"Enumerations","type":"groupMarker"},{"children":[{"title":"Enumeration Cases","type":"groupMarker"},{"path":"\/documentation\/paywall\/paywalloptions\/transactionbackgroundview-swift.enum\/spinner","title":"case spinner","type":"case"},{"title":"Default Implementations","type":"groupMarker"},{"children":[{"title":"Operators","type":"groupMarker"},{"path":"\/documentation\/paywall\/paywalloptions\/transactionbackgroundview-swift.enum\/!=(_:_:)","title":"static func != (Self, Self) -> Bool","type":"op"}],"path":"\/documentation\/paywall\/paywalloptions\/transactionbackgroundview-swift.enum\/equatable-implementations","title":"Equatable Implementations","type":"symbol"}],"path":"\/documentation\/paywall\/paywalloptions\/transactionbackgroundview-swift.enum","title":"PaywallOptions.TransactionBackgroundView","type":"enum"}],"path":"\/documentation\/paywall\/paywalloptions","title":"PaywallOptions","type":"class"}],"path":"\/documentation\/paywall\/gettingstarted","title":"Getting Started with Paywall","type":"symbol"},{"path":"\/documentation\/paywall\/triggering","title":"Triggering a Paywall","type":"article"},{"children":[{"title":"Configuring the SDK","type":"groupMarker"},{"children":[{"title":"The Delegate","type":"groupMarker"},{"children":[{"title":"Required Methods","type":"groupMarker"},{"path":"\/documentation\/paywall\/paywalldelegate\/purchase(product:)","title":"func purchase(product: SKProduct)","type":"method"},{"path":"\/documentation\/paywall\/paywalldelegate\/restorepurchases(completion:)","title":"func restorePurchases(completion: (Bool) -> Void)","type":"method"},{"path":"\/documentation\/paywall\/paywalldelegate\/isusersubscribed()","title":"func isUserSubscribed() -> Bool","type":"method"},{"title":"Optional Methods","type":"groupMarker"},{"path":"\/documentation\/paywall\/paywalldelegate\/trackanalyticsevent(withname:params:)","title":"func trackAnalyticsEvent(withName: String, params: [String : Any])","type":"method"},{"path":"\/documentation\/paywall\/paywalldelegate\/handlecustompaywallaction(withname:)","title":"func handleCustomPaywallAction(withName: String)","type":"method"},{"path":"\/documentation\/paywall\/paywalldelegate\/handlelog(level:scope:message:info:error:)","title":"func handleLog(level: String, scope: String, message: String?, info: [String : Any]?, error: Swift.Error?)","type":"method"},{"path":"\/documentation\/paywall\/paywalldelegate\/willdismisspaywall()","title":"func willDismissPaywall()","type":"method"},{"path":"\/documentation\/paywall\/paywalldelegate\/diddismisspaywall()","title":"func didDismissPaywall()","type":"method"},{"path":"\/documentation\/paywall\/paywalldelegate\/willpresentpaywall()","title":"func willPresentPaywall()","type":"method"},{"path":"\/documentation\/paywall\/paywalldelegate\/didpresentpaywall()","title":"func didPresentPaywall()","type":"method"},{"path":"\/documentation\/paywall\/paywalldelegate\/willopendeeplink(url:)","title":"func willOpenDeepLink(url: URL)","type":"method"},{"path":"\/documentation\/paywall\/paywalldelegate\/willopenurl(url:)","title":"func willOpenURL(url: URL)","type":"method"}],"path":"\/documentation\/paywall\/paywalldelegate","title":"PaywallDelegate","type":"protocol"},{"path":"\/documentation\/paywall\/custompaywallbuttons","title":"Custom Paywall Buttons","type":"article"},{"path":"\/documentation\/paywall\/thirdpartyanalytics","title":"Third-Party Analytics","type":"article"},{"title":"Setting the Paywall Options","type":"groupMarker"},{"children":[{"title":"Structures","type":"groupMarker"},{"children":[{"title":"Instance Properties","type":"groupMarker"},{"path":"\/documentation\/paywall\/paywalloptions\/logging-swift.struct\/level","title":"var level: LogLevel?","type":"property"},{"path":"\/documentation\/paywall\/paywalloptions\/logging-swift.struct\/scopes","title":"var scopes: Set<LogScope>","type":"property"}],"path":"\/documentation\/paywall\/paywalloptions\/logging-swift.struct","title":"PaywallOptions.Logging","type":"struct"},{"children":[{"title":"Instance Properties","type":"groupMarker"},{"path":"\/documentation\/paywall\/paywalloptions\/restorefailed-swift.struct\/closebuttontitle","title":"var closeButtonTitle: String","type":"property"},{"path":"\/documentation\/paywall\/paywalloptions\/restorefailed-swift.struct\/message","title":"var message: String","type":"property"},{"path":"\/documentation\/paywall\/paywalloptions\/restorefailed-swift.struct\/title","title":"var title: String","type":"property"}],"path":"\/documentation\/paywall\/paywalloptions\/restorefailed-swift.struct","title":"PaywallOptions.RestoreFailed","type":"struct"},{"title":"Instance Properties","type":"groupMarker"},{"path":"\/documentation\/paywall\/paywalloptions\/automaticallydismiss","title":"var automaticallyDismiss: Bool","type":"property"},{"path":"\/documentation\/paywall\/paywalloptions\/isexternaldatacollectionenabled","title":"var isExternalDataCollectionEnabled: Bool","type":"property"},{"path":"\/documentation\/paywall\/paywalloptions\/isgamecontrollerenabled","title":"var isGameControllerEnabled: Bool","type":"property"},{"path":"\/documentation\/paywall\/paywalloptions\/ishapticfeedbackenabled","title":"var isHapticFeedbackEnabled: Bool","type":"property"},{"path":"\/documentation\/paywall\/paywalloptions\/logging-swift.property","title":"var logging: PaywallOptions.Logging","type":"property"},{"path":"\/documentation\/paywall\/paywalloptions\/networkenvironment","title":"var networkEnvironment: PaywallNetworkEnvironment","type":"property"},{"path":"\/documentation\/paywall\/paywalloptions\/restorefailed-swift.property","title":"var restoreFailed: PaywallOptions.RestoreFailed","type":"property"},{"path":"\/documentation\/paywall\/paywalloptions\/shouldpreloadpaywalls","title":"var shouldPreloadPaywalls: Bool","type":"property"},{"path":"\/documentation\/paywall\/paywalloptions\/transactionbackgroundview-swift.property","title":"var transactionBackgroundView: TransactionBackgroundView?","type":"property"},{"title":"Enumerations","type":"groupMarker"},{"children":[{"title":"Enumeration Cases","type":"groupMarker"},{"path":"\/documentation\/paywall\/paywalloptions\/transactionbackgroundview-swift.enum\/spinner","title":"case spinner","type":"case"},{"title":"Default Implementations","type":"groupMarker"},{"children":[{"title":"Operators","type":"groupMarker"},{"path":"\/documentation\/paywall\/paywalloptions\/transactionbackgroundview-swift.enum\/!=(_:_:)","title":"static func != (Self, Self) -> Bool","type":"op"}],"path":"\/documentation\/paywall\/paywalloptions\/transactionbackgroundview-swift.enum\/equatable-implementations","title":"Equatable Implementations","type":"symbol"}],"path":"\/documentation\/paywall\/paywalloptions\/transactionbackgroundview-swift.enum","title":"PaywallOptions.TransactionBackgroundView","type":"enum"}],"path":"\/documentation\/paywall\/paywalloptions","title":"PaywallOptions","type":"class"}],"path":"\/documentation\/paywall\/gettingstarted","title":"Getting Started with Paywall","type":"symbol"},{"path":"\/documentation\/paywall\/ecosystem","title":"Understanding How Superwall Works","type":"article"},{"path":"\/documentation\/paywall\/paywall\/configure(apikey:userid:delegate:options:)","title":"static func configure(apiKey: String, userId: String?, delegate: PaywallDelegate?, options: PaywallOptions?) -> Paywall","type":"method"},{"children":[{"title":"Required Methods","type":"groupMarker"},{"path":"\/documentation\/paywall\/paywalldelegate\/purchase(product:)","title":"func purchase(product: SKProduct)","type":"method"},{"path":"\/documentation\/paywall\/paywalldelegate\/restorepurchases(completion:)","title":"func restorePurchases(completion: (Bool) -> Void)","type":"method"},{"path":"\/documentation\/paywall\/paywalldelegate\/isusersubscribed()","title":"func isUserSubscribed() -> Bool","type":"method"},{"title":"Optional Methods","type":"groupMarker"},{"path":"\/documentation\/paywall\/paywalldelegate\/trackanalyticsevent(withname:params:)","title":"func trackAnalyticsEvent(withName: String, params: [String : Any])","type":"method"},{"path":"\/documentation\/paywall\/paywalldelegate\/handlecustompaywallaction(withname:)","title":"func handleCustomPaywallAction(withName: String)","type":"method"},{"path":"\/documentation\/paywall\/paywalldelegate\/handlelog(level:scope:message:info:error:)","title":"func handleLog(level: String, scope: String, message: String?, info: [String : Any]?, error: Swift.Error?)","type":"method"},{"path":"\/documentation\/paywall\/paywalldelegate\/willdismisspaywall()","title":"func willDismissPaywall()","type":"method"},{"path":"\/documentation\/paywall\/paywalldelegate\/diddismisspaywall()","title":"func didDismissPaywall()","type":"method"},{"path":"\/documentation\/paywall\/paywalldelegate\/willpresentpaywall()","title":"func willPresentPaywall()","type":"method"},{"path":"\/documentation\/paywall\/paywalldelegate\/didpresentpaywall()","title":"func didPresentPaywall()","type":"method"},{"path":"\/documentation\/paywall\/paywalldelegate\/willopendeeplink(url:)","title":"func willOpenDeepLink(url: URL)","type":"method"},{"path":"\/documentation\/paywall\/paywalldelegate\/willopenurl(url:)","title":"func willOpenURL(url: URL)","type":"method"}],"path":"\/documentation\/paywall\/paywalldelegate","title":"PaywallDelegate","type":"protocol"},{"path":"\/documentation\/paywall\/paywall\/delegate","title":"static var delegate: PaywallDelegate?","type":"property"},{"children":[{"title":"Structures","type":"groupMarker"},{"children":[{"title":"Instance Properties","type":"groupMarker"},{"path":"\/documentation\/paywall\/paywalloptions\/logging-swift.struct\/level","title":"var level: LogLevel?","type":"property"},{"path":"\/documentation\/paywall\/paywalloptions\/logging-swift.struct\/scopes","title":"var scopes: Set<LogScope>","type":"property"}],"path":"\/documentation\/paywall\/paywalloptions\/logging-swift.struct","title":"PaywallOptions.Logging","type":"struct"},{"children":[{"title":"Instance Properties","type":"groupMarker"},{"path":"\/documentation\/paywall\/paywalloptions\/restorefailed-swift.struct\/closebuttontitle","title":"var closeButtonTitle: String","type":"property"},{"path":"\/documentation\/paywall\/paywalloptions\/restorefailed-swift.struct\/message","title":"var message: String","type":"property"},{"path":"\/documentation\/paywall\/paywalloptions\/restorefailed-swift.struct\/title","title":"var title: String","type":"property"}],"path":"\/documentation\/paywall\/paywalloptions\/restorefailed-swift.struct","title":"PaywallOptions.RestoreFailed","type":"struct"},{"title":"Instance Properties","type":"groupMarker"},{"path":"\/documentation\/paywall\/paywalloptions\/automaticallydismiss","title":"var automaticallyDismiss: Bool","type":"property"},{"path":"\/documentation\/paywall\/paywalloptions\/isexternaldatacollectionenabled","title":"var isExternalDataCollectionEnabled: Bool","type":"property"},{"path":"\/documentation\/paywall\/paywalloptions\/isgamecontrollerenabled","title":"var isGameControllerEnabled: Bool","type":"property"},{"path":"\/documentation\/paywall\/paywalloptions\/ishapticfeedbackenabled","title":"var isHapticFeedbackEnabled: Bool","type":"property"},{"path":"\/documentation\/paywall\/paywalloptions\/logging-swift.property","title":"var logging: PaywallOptions.Logging","type":"property"},{"path":"\/documentation\/paywall\/paywalloptions\/networkenvironment","title":"var networkEnvironment: PaywallNetworkEnvironment","type":"property"},{"path":"\/documentation\/paywall\/paywalloptions\/restorefailed-swift.property","title":"var restoreFailed: PaywallOptions.RestoreFailed","type":"property"},{"path":"\/documentation\/paywall\/paywalloptions\/shouldpreloadpaywalls","title":"var shouldPreloadPaywalls: Bool","type":"property"},{"path":"\/documentation\/paywall\/paywalloptions\/transactionbackgroundview-swift.property","title":"var transactionBackgroundView: TransactionBackgroundView?","type":"property"},{"title":"Enumerations","type":"groupMarker"},{"children":[{"title":"Enumeration Cases","type":"groupMarker"},{"path":"\/documentation\/paywall\/paywalloptions\/transactionbackgroundview-swift.enum\/spinner","title":"case spinner","type":"case"},{"title":"Default Implementations","type":"groupMarker"},{"children":[{"title":"Operators","type":"groupMarker"},{"path":"\/documentation\/paywall\/paywalloptions\/transactionbackgroundview-swift.enum\/!=(_:_:)","title":"static func != (Self, Self) -> Bool","type":"op"}],"path":"\/documentation\/paywall\/paywalloptions\/transactionbackgroundview-swift.enum\/equatable-implementations","title":"Equatable Implementations","type":"symbol"}],"path":"\/documentation\/paywall\/paywalloptions\/transactionbackgroundview-swift.enum","title":"PaywallOptions.TransactionBackgroundView","type":"enum"}],"path":"\/documentation\/paywall\/paywalloptions","title":"PaywallOptions","type":"class"},{"path":"\/documentation\/paywall\/paywall\/options","title":"static var options: PaywallOptions","type":"property"},{"children":[{"title":"Enumeration Cases","type":"groupMarker"},{"path":"\/documentation\/paywall\/paywalloptions\/paywallnetworkenvironment\/developer","title":"case developer","type":"case"},{"path":"\/documentation\/paywall\/paywalloptions\/paywallnetworkenvironment\/release","title":"case release","type":"case"},{"path":"\/documentation\/paywall\/paywalloptions\/paywallnetworkenvironment\/releasecandidate","title":"case releaseCandidate","type":"case"},{"title":"Default Implementations","type":"groupMarker"},{"children":[{"title":"Operators","type":"groupMarker"},{"path":"\/documentation\/paywall\/paywalloptions\/paywallnetworkenvironment\/!=(_:_:)","title":"static func != (Self, Self) -> Bool","type":"op"}],"path":"\/documentation\/paywall\/paywalloptions\/paywallnetworkenvironment\/equatable-implementations","title":"Equatable Implementations","type":"symbol"}],"path":"\/documentation\/paywall\/paywalloptions\/paywallnetworkenvironment","title":"PaywallOptions.PaywallNetworkEnvironment","type":"enum"},{"title":"Triggering and Dismissing a Paywall","type":"groupMarker"},{"path":"\/documentation\/paywall\/triggering","title":"Triggering a Paywall","type":"article"},{"path":"\/documentation\/paywall\/paywall\/trigger(event:params:on:products:ignoresubscriptionstatus:presentationstyleoverride:onskip:onpresent:ondismiss:)","title":"static func trigger(event: String?, params: [String : Any]?, on: UIViewController?, products: PaywallProducts?, ignoreSubscriptionStatus: Bool, presentationStyleOverride: PaywallPresentationStyle, onSkip: ((NSError?) -> Void)?, onPresent: ((PaywallInfo?) -> Void)?, onDismiss: ((Bool, String?, PaywallInfo?) -> Void)?)","type":"method"},{"path":"\/documentation\/paywall\/paywall\/track(_:_:)-2vkwo","title":"static func track(String, [String : Any])","type":"method"},{"path":"\/documentation\/paywall\/paywall\/dismiss(_:)","title":"static func dismiss((() -> Void)?)","type":"method"},{"children":[{"title":"Instance Properties","type":"groupMarker"},{"path":"\/documentation\/paywall\/paywallinfo\/experiment","title":"let experiment: Experiment?","type":"property"},{"path":"\/documentation\/paywall\/paywallinfo\/identifier","title":"let identifier: String","type":"property"},{"path":"\/documentation\/paywall\/paywallinfo\/name","title":"let name: String","type":"property"},{"path":"\/documentation\/paywall\/paywallinfo\/paywalljsversion","title":"let paywalljsVersion: String?","type":"property"},{"path":"\/documentation\/paywall\/paywallinfo\/presentedby","title":"let presentedBy: String","type":"property"},{"path":"\/documentation\/paywall\/paywallinfo\/presentedbyeventat","title":"let presentedByEventAt: String?","type":"property"},{"path":"\/documentation\/paywall\/paywallinfo\/presentedbyeventwithid","title":"let presentedByEventWithId: String?","type":"property"},{"path":"\/documentation\/paywall\/paywallinfo\/presentedbyeventwithname","title":"let presentedByEventWithName: String?","type":"property"},{"path":"\/documentation\/paywall\/paywallinfo\/productids","title":"let productIds: [String]","type":"property"},{"path":"\/documentation\/paywall\/paywallinfo\/productsloadcompletetime","title":"let productsLoadCompleteTime: String?","type":"property"},{"path":"\/documentation\/paywall\/paywallinfo\/productsloadduration","title":"let productsLoadDuration: TimeInterval?","type":"property"},{"path":"\/documentation\/paywall\/paywallinfo\/productsloadfailtime","title":"let productsLoadFailTime: String?","type":"property"},{"path":"\/documentation\/paywall\/paywallinfo\/productsloadstarttime","title":"let productsLoadStartTime: String?","type":"property"},{"path":"\/documentation\/paywall\/paywallinfo\/responseloadcompletetime","title":"let responseLoadCompleteTime: String?","type":"property"},{"path":"\/documentation\/paywall\/paywallinfo\/responseloadduration","title":"let responseLoadDuration: TimeInterval?","type":"property"},{"path":"\/documentation\/paywall\/paywallinfo\/responseloadstarttime","title":"let responseLoadStartTime: String?","type":"property"},{"path":"\/documentation\/paywall\/paywallinfo\/slug","title":"let slug: String","type":"property"},{"path":"\/documentation\/paywall\/paywallinfo\/url","title":"let url: URL?","type":"property"},{"path":"\/documentation\/paywall\/paywallinfo\/webviewloadcompletetime","title":"let webViewLoadCompleteTime: String?","type":"property"},{"path":"\/documentation\/paywall\/paywallinfo\/webviewloadduration","title":"let webViewLoadDuration: TimeInterval?","type":"property"},{"path":"\/documentation\/paywall\/paywallinfo\/webviewloadstarttime","title":"let webViewLoadStartTime: String?","type":"property"}],"path":"\/documentation\/paywall\/paywallinfo","title":"PaywallInfo","type":"class"},{"children":[{"title":"Enumeration Cases","type":"groupMarker"},{"path":"\/documentation\/paywall\/paywall\/eventname\/appclose","title":"case appClose","type":"case"},{"path":"\/documentation\/paywall\/paywall\/eventname\/appinstall","title":"case appInstall","type":"case"},{"path":"\/documentation\/paywall\/paywall\/eventname\/applaunch","title":"case appLaunch","type":"case"},{"path":"\/documentation\/paywall\/paywall\/eventname\/appopen","title":"case appOpen","type":"case"},{"path":"\/documentation\/paywall\/paywall\/eventname\/deeplink","title":"case deepLink","type":"case"},{"path":"\/documentation\/paywall\/paywall\/eventname\/firstseen","title":"case firstSeen","type":"case"},{"path":"\/documentation\/paywall\/paywall\/eventname\/freetrialstart","title":"case freeTrialStart","type":"case"},{"path":"\/documentation\/paywall\/paywall\/eventname\/manualpresent","title":"case manualPresent","type":"case"},{"path":"\/documentation\/paywall\/paywall\/eventname\/nonrecurringproductpurchase","title":"case nonRecurringProductPurchase","type":"case"},{"path":"\/documentation\/paywall\/paywall\/eventname\/paywallclose","title":"case paywallClose","type":"case"},{"path":"\/documentation\/paywall\/paywall\/eventname\/paywallopen","title":"case paywallOpen","type":"case"},{"path":"\/documentation\/paywall\/paywall\/eventname\/paywallproductsloadcomplete","title":"case paywallProductsLoadComplete","type":"case"},{"path":"\/documentation\/paywall\/paywall\/eventname\/paywallproductsloadfail","title":"case paywallProductsLoadFail","type":"case"},{"path":"\/documentation\/paywall\/paywall\/eventname\/paywallproductsloadstart","title":"case paywallProductsLoadStart","type":"case"},{"path":"\/documentation\/paywall\/paywall\/eventname\/paywallresponseloadcomplete","title":"case paywallResponseLoadComplete","type":"case"},{"path":"\/documentation\/paywall\/paywall\/eventname\/paywallresponseloadfail","title":"case paywallResponseLoadFail","type":"case"},{"path":"\/documentation\/paywall\/paywall\/eventname\/paywallresponseloadnotfound","title":"case paywallResponseLoadNotFound","type":"case"},{"path":"\/documentation\/paywall\/paywall\/eventname\/paywallresponseloadstart","title":"case paywallResponseLoadStart","type":"case"},{"path":"\/documentation\/paywall\/paywall\/eventname\/paywallwebviewloadcomplete","title":"case paywallWebviewLoadComplete","type":"case"},{"path":"\/documentation\/paywall\/paywall\/eventname\/paywallwebviewloadfail","title":"case paywallWebviewLoadFail","type":"case"},{"path":"\/documentation\/paywall\/paywall\/eventname\/paywallwebviewloadstart","title":"case paywallWebviewLoadStart","type":"case"},{"path":"\/documentation\/paywall\/paywall\/eventname\/paywallwebviewloadtimeout","title":"case paywallWebviewLoadTimeout","type":"case"},{"path":"\/documentation\/paywall\/paywall\/eventname\/sessionstart","title":"case sessionStart","type":"case"},{"path":"\/documentation\/paywall\/paywall\/eventname\/subscriptionstart","title":"case subscriptionStart","type":"case"},{"path":"\/documentation\/paywall\/paywall\/eventname\/transactionabandon","title":"case transactionAbandon","type":"case"},{"path":"\/documentation\/paywall\/paywall\/eventname\/transactioncomplete","title":"case transactionComplete","type":"case"},{"path":"\/documentation\/paywall\/paywall\/eventname\/transactionfail","title":"case transactionFail","type":"case"},{"path":"\/documentation\/paywall\/paywall\/eventname\/transactionrestore","title":"case transactionRestore","type":"case"},{"path":"\/documentation\/paywall\/paywall\/eventname\/transactionstart","title":"case transactionStart","type":"case"},{"path":"\/documentation\/paywall\/paywall\/eventname\/triggerfire","title":"case triggerFire","type":"case"},{"path":"\/documentation\/paywall\/paywall\/eventname\/userattributes","title":"case userAttributes","type":"case"},{"title":"Initializers","type":"groupMarker"},{"path":"\/documentation\/paywall\/paywall\/eventname\/init(rawvalue:)","title":"init?(rawValue: String)","type":"init"},{"title":"Default Implementations","type":"groupMarker"},{"children":[{"title":"Operators","type":"groupMarker"},{"path":"\/documentation\/paywall\/paywall\/eventname\/!=(_:_:)","title":"static func != (Self, Self) -> Bool","type":"op"}],"path":"\/documentation\/paywall\/paywall\/eventname\/equatable-implementations","title":"Equatable Implementations","type":"symbol"},{"children":[{"title":"Instance Properties","type":"groupMarker"},{"path":"\/documentation\/paywall\/paywall\/eventname\/hashvalue","title":"var hashValue: Int","type":"property"},{"title":"Instance Methods","type":"groupMarker"},{"path":"\/documentation\/paywall\/paywall\/eventname\/hash(into:)","title":"func hash(into: inout Hasher)","type":"method"}],"path":"\/documentation\/paywall\/paywall\/eventname\/rawrepresentable-implementations","title":"RawRepresentable Implementations","type":"symbol"}],"path":"\/documentation\/paywall\/paywall\/eventname","title":"Paywall.EventName","type":"enum"},{"path":"\/documentation\/paywall\/paywall\/track(_:_:)-7gc4r","title":"static func track(StandardEvent, [String : Any])","type":"method"},{"path":"\/documentation\/paywall\/paywall\/track(name:params:)","title":"static func track(name: String, params: NSDictionary?)","type":"method"},{"children":[{"title":"Enumeration Cases","type":"groupMarker"},{"path":"\/documentation\/paywall\/paywall\/standardevent\/base(name:params:)","title":"case base(name: String, params: [String : Any])","type":"case"},{"path":"\/documentation\/paywall\/paywall\/standardevent\/coresessionabandon","title":"case coreSessionAbandon","type":"case"},{"path":"\/documentation\/paywall\/paywall\/standardevent\/coresessioncomplete","title":"case coreSessionComplete","type":"case"},{"path":"\/documentation\/paywall\/paywall\/standardevent\/coresessionstart","title":"case coreSessionStart","type":"case"},{"path":"\/documentation\/paywall\/paywall\/standardevent\/deeplinkopen(deeplinkurl:)","title":"case deepLinkOpen(deepLinkUrl: URL)","type":"case"},{"path":"\/documentation\/paywall\/paywall\/standardevent\/login","title":"case logIn","type":"case"},{"path":"\/documentation\/paywall\/paywall\/standardevent\/logout","title":"case logOut","type":"case"},{"path":"\/documentation\/paywall\/paywall\/standardevent\/onboardingcomplete","title":"case onboardingComplete","type":"case"},{"path":"\/documentation\/paywall\/paywall\/standardevent\/onboardingstart","title":"case onboardingStart","type":"case"},{"path":"\/documentation\/paywall\/paywall\/standardevent\/pushnotificationopen(superwallid:)","title":"case pushNotificationOpen(superwallId: String?)","type":"case"},{"path":"\/documentation\/paywall\/paywall\/standardevent\/pushnotificationreceive(superwallid:)","title":"case pushNotificationReceive(superwallId: String?)","type":"case"},{"path":"\/documentation\/paywall\/paywall\/standardevent\/signup","title":"case signUp","type":"case"},{"path":"\/documentation\/paywall\/paywall\/standardevent\/userattributes(standard:custom:)","title":"case userAttributes(standard: [StandardUserAttributeKey : Any?], custom: [String : Any?])","type":"case"}],"path":"\/documentation\/paywall\/paywall\/standardevent","title":"Paywall.StandardEvent","type":"enum"},{"title":"In-App Previews","type":"groupMarker"},{"path":"\/documentation\/paywall\/inapppreviews","title":"In-App Previews","type":"article"},{"path":"\/documentation\/paywall\/paywall\/handledeeplink(_:)","title":"static func handleDeepLink(URL)","type":"method"},{"title":"Presenting and Dismissing a Paywall","type":"groupMarker"},{"path":"\/documentation\/paywall\/paywall\/present(onpresent:ondismiss:onfail:)","title":"static func present(onPresent: ((PaywallInfo?) -> Void)?, onDismiss: ((Bool, String?, PaywallInfo?) -> Void)?, onFail: ((NSError?) -> Void)?)","type":"method"},{"path":"\/documentation\/paywall\/paywall\/present(on:onpresent:ondismiss:onfail:)","title":"static func present(on: UIViewController?, onPresent: ((PaywallInfo?) -> Void)?, onDismiss: ((Bool, String?, PaywallInfo?) -> Void)?, onFail: ((NSError?) -> Void)?)","type":"method"},{"path":"\/documentation\/paywall\/paywall\/present(identifier:on:ignoresubscriptionstatus:presentationstyleoverride:onpresent:ondismiss:onfail:)","title":"static func present(identifier: String?, on: UIViewController?, ignoreSubscriptionStatus: Bool, presentationStyleOverride: PaywallPresentationStyle, onPresent: ((PaywallInfo?) -> Void)?, onDismiss: ((Bool, String?, PaywallInfo?) -> Void)?, onFail: ((NSError?) -> Void)?)","type":"method"},{"path":"\/documentation\/paywall\/paywall\/load(identifier:)","title":"static func load(identifier: String)","type":"method"},{"title":"Identifying a User","type":"groupMarker"},{"path":"\/documentation\/paywall\/settinguserattributes","title":"Setting User Attributes","type":"article"},{"path":"\/documentation\/paywall\/paywall\/identify(userid:)","title":"static func identify(userId: String) -> Paywall","type":"method"},{"path":"\/documentation\/paywall\/paywall\/setuserattributes(_:)","title":"static func setUserAttributes([String : Any?])","type":"method"},{"path":"\/documentation\/paywall\/paywall\/userattributes","title":"static var userAttributes: [String : Any]","type":"property"},{"path":"\/documentation\/paywall\/paywall\/reset()","title":"static func reset() -> Paywall","type":"method"},{"path":"\/documentation\/paywall\/paywall\/setuserattributesdictionary(attributes:)","title":"static func setUserAttributesDictionary(attributes: NSDictionary)","type":"method"},{"children":[{"title":"Enumeration Cases","type":"groupMarker"},{"path":"\/documentation\/paywall\/paywall\/standarduserattribute\/apnstoken(_:)","title":"case apnsToken(String)","type":"case"},{"path":"\/documentation\/paywall\/paywall\/standarduserattribute\/createdat(_:)","title":"case createdAt(Date)","type":"case"},{"path":"\/documentation\/paywall\/paywall\/standarduserattribute\/email(_:)","title":"case email(String)","type":"case"},{"path":"\/documentation\/paywall\/paywall\/standarduserattribute\/fcmtoken(_:)","title":"case fcmToken(String)","type":"case"},{"path":"\/documentation\/paywall\/paywall\/standarduserattribute\/firstname(_:)","title":"case firstName(String)","type":"case"},{"path":"\/documentation\/paywall\/paywall\/standarduserattribute\/fullphone(_:)","title":"case fullPhone(String)","type":"case"},{"path":"\/documentation\/paywall\/paywall\/standarduserattribute\/id(_:)","title":"case id(String)","type":"case"},{"path":"\/documentation\/paywall\/paywall\/standarduserattribute\/lastname(_:)","title":"case lastName(String)","type":"case"},{"path":"\/documentation\/paywall\/paywall\/standarduserattribute\/phone(_:)","title":"case phone(String)","type":"case"},{"path":"\/documentation\/paywall\/paywall\/standarduserattribute\/phonecountrycode(_:)","title":"case phoneCountryCode(String)","type":"case"}],"path":"\/documentation\/paywall\/paywall\/standarduserattribute","title":"Paywall.StandardUserAttribute","type":"enum"},{"children":[{"title":"Enumeration Cases","type":"groupMarker"},{"path":"\/documentation\/paywall\/paywall\/standarduserattributekey\/apnstoken","title":"case apnsToken","type":"case"},{"path":"\/documentation\/paywall\/paywall\/standarduserattributekey\/applicationinstalledat","title":"case applicationInstalledAt","type":"case"},{"path":"\/documentation\/paywall\/paywall\/standarduserattributekey\/createdat","title":"case createdAt","type":"case"},{"path":"\/documentation\/paywall\/paywall\/standarduserattributekey\/email","title":"case email","type":"case"},{"path":"\/documentation\/paywall\/paywall\/standarduserattributekey\/fcmtoken","title":"case fcmToken","type":"case"},{"path":"\/documentation\/paywall\/paywall\/standarduserattributekey\/firstname","title":"case firstName","type":"case"},{"path":"\/documentation\/paywall\/paywall\/standarduserattributekey\/fullphone","title":"case fullPhone","type":"case"},{"path":"\/documentation\/paywall\/paywall\/standarduserattributekey\/id","title":"case id","type":"case"},{"path":"\/documentation\/paywall\/paywall\/standarduserattributekey\/lastname","title":"case lastName","type":"case"},{"path":"\/documentation\/paywall\/paywall\/standarduserattributekey\/phone","title":"case phone","type":"case"},{"path":"\/documentation\/paywall\/paywall\/standarduserattributekey\/phonecountrycode","title":"case phoneCountryCode","type":"case"},{"title":"Initializers","type":"groupMarker"},{"path":"\/documentation\/paywall\/paywall\/standarduserattributekey\/init(rawvalue:)","title":"init?(rawValue: String)","type":"init"},{"title":"Default Implementations","type":"groupMarker"},{"children":[{"title":"Operators","type":"groupMarker"},{"path":"\/documentation\/paywall\/paywall\/standarduserattributekey\/!=(_:_:)","title":"static func != (Self, Self) -> Bool","type":"op"}],"path":"\/documentation\/paywall\/paywall\/standarduserattributekey\/equatable-implementations","title":"Equatable Implementations","type":"symbol"},{"children":[{"title":"Instance Properties","type":"groupMarker"},{"path":"\/documentation\/paywall\/paywall\/standarduserattributekey\/hashvalue","title":"var hashValue: Int","type":"property"},{"title":"Instance Methods","type":"groupMarker"},{"path":"\/documentation\/paywall\/paywall\/standarduserattributekey\/hash(into:)","title":"func hash(into: inout Hasher)","type":"method"}],"path":"\/documentation\/paywall\/paywall\/standarduserattributekey\/rawrepresentable-implementations","title":"RawRepresentable Implementations","type":"symbol"}],"path":"\/documentation\/paywall\/paywall\/standarduserattributekey","title":"Paywall.StandardUserAttributeKey","type":"enum"},{"path":"\/documentation\/paywall\/paywall\/setuserattributes(_:custom:)","title":"static func setUserAttributes(StandardUserAttribute..., custom: [String : Any?])","type":"method"},{"title":"Game Controller","type":"groupMarker"},{"path":"\/documentation\/paywall\/gamecontrollersupport","title":"Game Controller Support","type":"article"},{"path":"\/documentation\/paywall\/paywall\/gamepadvaluechanged(gamepad:element:)","title":"static func gamepadValueChanged(gamepad: GCExtendedGamepad, element: GCControllerElement)","type":"method"},{"path":"\/documentation\/paywall\/paywall\/isgamecontrollerenabled","title":"static var isGameControllerEnabled: Bool","type":"property"},{"title":"Logging","type":"groupMarker"},{"path":"\/documentation\/paywall\/paywalldelegate\/handlelog(level:scope:message:info:error:)","title":"func handleLog(level: String, scope: String, message: String?, info: [String : Any]?, error: Swift.Error?)","type":"method"},{"path":"\/documentation\/paywall\/paywall\/loglevel","title":"static var logLevel: LogLevel?","type":"property"},{"path":"\/documentation\/paywall\/paywall\/logscopes","title":"static var logScopes: Set<LogScope>","type":"property"},{"path":"\/documentation\/paywall\/paywall\/debugmode","title":"static var debugMode: Bool","type":"property"},{"title":"Customization","type":"groupMarker"},{"path":"\/documentation\/paywall\/paywall\/localizationoverride(localeidentifier:)","title":"static func localizationOverride(localeIdentifier: String?)","type":"method"},{"path":"\/documentation\/paywall\/paywall\/presentedviewcontroller","title":"static var presentedViewController: UIViewController?","type":"property"},{"path":"\/documentation\/paywall\/paywall\/automaticallydismiss","title":"static var automaticallyDismiss: Bool","type":"property"},{"path":"\/documentation\/paywall\/paywall\/restorefailedtitlestring","title":"static var restoreFailedTitleString: String","type":"property"},{"path":"\/documentation\/paywall\/paywall\/restorefailedmessagestring","title":"static var restoreFailedMessageString: String","type":"property"},{"path":"\/documentation\/paywall\/paywall\/restorefailedclosebuttonstring","title":"static var restoreFailedCloseButtonString: String","type":"property"},{"path":"\/documentation\/paywall\/paywall\/networkenvironment","title":"static var networkEnvironment: PaywallOptions.PaywallNetworkEnvironment","type":"property"},{"path":"\/documentation\/paywall\/paywall\/shouldpreloadtriggers","title":"static var shouldPreloadTriggers: Bool","type":"property"},{"path":"\/documentation\/paywall\/paywall\/shouldanimatepaywalldismissal","title":"static var shouldAnimatePaywallDismissal: Bool","type":"property"},{"path":"\/documentation\/paywall\/paywall\/shouldanimatepaywallpresentation","title":"static var shouldAnimatePaywallPresentation: Bool","type":"property"},{"title":"Type Properties","type":"groupMarker"},{"path":"\/documentation\/paywall\/paywall\/latestpaywallinfo","title":"static var latestPaywallInfo: PaywallInfo?","type":"property"},{"path":"\/documentation\/paywall\/paywall\/userid","title":"static var userId: String?","type":"property"},{"title":"Type Methods","type":"groupMarker"},{"path":"\/documentation\/paywall\/paywall\/preloadallpaywalls()","title":"static func preloadAllPaywalls()","type":"method"},{"path":"\/documentation\/paywall\/paywall\/preloadpaywalls(fortriggers:)","title":"static func preloadPaywalls(forTriggers: Set<String>)","type":"method"},{"title":"Default Implementations","type":"groupMarker"},{"children":[{"title":"Instance Methods","type":"groupMarker"},{"path":"\/documentation\/paywall\/paywall\/paymentqueue(_:restorecompletedtransactionsfailedwitherror:)","title":"func paymentQueue(SKPaymentQueue, restoreCompletedTransactionsFailedWithError: Error)","type":"method"},{"path":"\/documentation\/paywall\/paywall\/paymentqueue(_:updatedtransactions:)","title":"func paymentQueue(SKPaymentQueue, updatedTransactions: [SKPaymentTransaction])","type":"method"},{"path":"\/documentation\/paywall\/paywall\/paymentqueuerestorecompletedtransactionsfinished(_:)","title":"func paymentQueueRestoreCompletedTransactionsFinished(SKPaymentQueue)","type":"method"}],"path":"\/documentation\/paywall\/paywall\/skpaymenttransactionobserver-implementations","title":"SKPaymentTransactionObserver Implementations","type":"symbol"}],"path":"\/documentation\/paywall\/paywall","title":"Paywall","type":"class"},{"children":[{"title":"Structures","type":"groupMarker"},{"children":[{"title":"Instance Properties","type":"groupMarker"},{"path":"\/documentation\/paywall\/paywalloptions\/logging-swift.struct\/level","title":"var level: LogLevel?","type":"property"},{"path":"\/documentation\/paywall\/paywalloptions\/logging-swift.struct\/scopes","title":"var scopes: Set<LogScope>","type":"property"}],"path":"\/documentation\/paywall\/paywalloptions\/logging-swift.struct","title":"PaywallOptions.Logging","type":"struct"},{"children":[{"title":"Instance Properties","type":"groupMarker"},{"path":"\/documentation\/paywall\/paywalloptions\/restorefailed-swift.struct\/closebuttontitle","title":"var closeButtonTitle: String","type":"property"},{"path":"\/documentation\/paywall\/paywalloptions\/restorefailed-swift.struct\/message","title":"var message: String","type":"property"},{"path":"\/documentation\/paywall\/paywalloptions\/restorefailed-swift.struct\/title","title":"var title: String","type":"property"}],"path":"\/documentation\/paywall\/paywalloptions\/restorefailed-swift.struct","title":"PaywallOptions.RestoreFailed","type":"struct"},{"title":"Instance Properties","type":"groupMarker"},{"path":"\/documentation\/paywall\/paywalloptions\/automaticallydismiss","title":"var automaticallyDismiss: Bool","type":"property"},{"path":"\/documentation\/paywall\/paywalloptions\/isexternaldatacollectionenabled","title":"var isExternalDataCollectionEnabled: Bool","type":"property"},{"path":"\/documentation\/paywall\/paywalloptions\/isgamecontrollerenabled","title":"var isGameControllerEnabled: Bool","type":"property"},{"path":"\/documentation\/paywall\/paywalloptions\/ishapticfeedbackenabled","title":"var isHapticFeedbackEnabled: Bool","type":"property"},{"path":"\/documentation\/paywall\/paywalloptions\/logging-swift.property","title":"var logging: PaywallOptions.Logging","type":"property"},{"path":"\/documentation\/paywall\/paywalloptions\/networkenvironment","title":"var networkEnvironment: PaywallNetworkEnvironment","type":"property"},{"path":"\/documentation\/paywall\/paywalloptions\/restorefailed-swift.property","title":"var restoreFailed: PaywallOptions.RestoreFailed","type":"property"},{"path":"\/documentation\/paywall\/paywalloptions\/shouldpreloadpaywalls","title":"var shouldPreloadPaywalls: Bool","type":"property"},{"path":"\/documentation\/paywall\/paywalloptions\/transactionbackgroundview-swift.property","title":"var transactionBackgroundView: TransactionBackgroundView?","type":"property"},{"title":"Enumerations","type":"groupMarker"},{"children":[{"title":"Enumeration Cases","type":"groupMarker"},{"path":"\/documentation\/paywall\/paywalloptions\/transactionbackgroundview-swift.enum\/spinner","title":"case spinner","type":"case"},{"title":"Default Implementations","type":"groupMarker"},{"children":[{"title":"Operators","type":"groupMarker"},{"path":"\/documentation\/paywall\/paywalloptions\/transactionbackgroundview-swift.enum\/!=(_:_:)","title":"static func != (Self, Self) -> Bool","type":"op"}],"path":"\/documentation\/paywall\/paywalloptions\/transactionbackgroundview-swift.enum\/equatable-implementations","title":"Equatable Implementations","type":"symbol"}],"path":"\/documentation\/paywall\/paywalloptions\/transactionbackgroundview-swift.enum","title":"PaywallOptions.TransactionBackgroundView","type":"enum"}],"path":"\/documentation\/paywall\/paywalloptions","title":"PaywallOptions","type":"class"},{"title":"The Delegate","type":"groupMarker"},{"children":[{"title":"Required Methods","type":"groupMarker"},{"path":"\/documentation\/paywall\/paywalldelegate\/purchase(product:)","title":"func purchase(product: SKProduct)","type":"method"},{"path":"\/documentation\/paywall\/paywalldelegate\/restorepurchases(completion:)","title":"func restorePurchases(completion: (Bool) -> Void)","type":"method"},{"path":"\/documentation\/paywall\/paywalldelegate\/isusersubscribed()","title":"func isUserSubscribed() -> Bool","type":"method"},{"title":"Optional Methods","type":"groupMarker"},{"path":"\/documentation\/paywall\/paywalldelegate\/trackanalyticsevent(withname:params:)","title":"func trackAnalyticsEvent(withName: String, params: [String : Any])","type":"method"},{"path":"\/documentation\/paywall\/paywalldelegate\/handlecustompaywallaction(withname:)","title":"func handleCustomPaywallAction(withName: String)","type":"method"},{"path":"\/documentation\/paywall\/paywalldelegate\/handlelog(level:scope:message:info:error:)","title":"func handleLog(level: String, scope: String, message: String?, info: [String : Any]?, error: Swift.Error?)","type":"method"},{"path":"\/documentation\/paywall\/paywalldelegate\/willdismisspaywall()","title":"func willDismissPaywall()","type":"method"},{"path":"\/documentation\/paywall\/paywalldelegate\/diddismisspaywall()","title":"func didDismissPaywall()","type":"method"},{"path":"\/documentation\/paywall\/paywalldelegate\/willpresentpaywall()","title":"func willPresentPaywall()","type":"method"},{"path":"\/documentation\/paywall\/paywalldelegate\/didpresentpaywall()","title":"func didPresentPaywall()","type":"method"},{"path":"\/documentation\/paywall\/paywalldelegate\/willopendeeplink(url:)","title":"func willOpenDeepLink(url: URL)","type":"method"},{"path":"\/documentation\/paywall\/paywalldelegate\/willopenurl(url:)","title":"func willOpenURL(url: URL)","type":"method"}],"path":"\/documentation\/paywall\/paywalldelegate","title":"PaywallDelegate","type":"protocol"},{"path":"\/documentation\/paywall\/custompaywallbuttons","title":"Custom Paywall Buttons","type":"article"},{"path":"\/documentation\/paywall\/thirdpartyanalytics","title":"Third-Party Analytics","type":"article"},{"title":"Articles","type":"groupMarker"},{"path":"\/documentation\/paywall\/automaticallytrackedevents","title":"Automatically Tracked Events","type":"article"},{"title":"Classes","type":"groupMarker"},{"children":[{"title":"Initializers","type":"groupMarker"},{"path":"\/documentation\/paywall\/paywallproducts\/init(primary:secondary:tertiary:)","title":"init(primary: SKProduct?, secondary: SKProduct?, tertiary: SKProduct?)","type":"init"}],"path":"\/documentation\/paywall\/paywallproducts","title":"PaywallProducts","type":"class"},{"title":"Structures","type":"groupMarker"},{"children":[{"title":"Structures","type":"groupMarker"},{"children":[{"title":"Initializers","type":"groupMarker"},{"path":"\/documentation\/paywall\/experiment\/variant-swift.struct\/init(from:)","title":"init(from: Decoder) throws","type":"init"},{"title":"Instance Properties","type":"groupMarker"},{"path":"\/documentation\/paywall\/experiment\/variant-swift.struct\/id","title":"let id: String","type":"property"},{"path":"\/documentation\/paywall\/experiment\/variant-swift.struct\/paywallid","title":"let paywallId: String?","type":"property"},{"path":"\/documentation\/paywall\/experiment\/variant-swift.struct\/type","title":"let type: VariantType","type":"property"},{"title":"Enumerations","type":"groupMarker"},{"children":[{"title":"Enumeration Cases","type":"groupMarker"},{"path":"\/documentation\/paywall\/experiment\/variant-swift.struct\/varianttype\/holdout","title":"case holdout","type":"case"},{"path":"\/documentation\/paywall\/experiment\/variant-swift.struct\/varianttype\/treatment","title":"case treatment","type":"case"},{"title":"Initializers","type":"groupMarker"},{"path":"\/documentation\/paywall\/experiment\/variant-swift.struct\/varianttype\/init(from:)-79bw4","title":"init(from: Decoder) throws","type":"init"},{"path":"\/documentation\/paywall\/experiment\/variant-swift.struct\/varianttype\/init(rawvalue:)","title":"init?(rawValue: String)","type":"init"},{"title":"Default Implementations","type":"groupMarker"},{"children":[{"title":"Operators","type":"groupMarker"},{"path":"\/documentation\/paywall\/experiment\/variant-swift.struct\/varianttype\/!=(_:_:)","title":"static func != (Self, Self) -> Bool","type":"op"}],"path":"\/documentation\/paywall\/experiment\/variant-swift.struct\/varianttype\/equatable-implementations","title":"Equatable Implementations","type":"symbol"},{"children":[{"title":"Initializers","type":"groupMarker"},{"path":"\/documentation\/paywall\/experiment\/variant-swift.struct\/varianttype\/init(from:)-1oi6d","title":"init(from: Decoder) throws","type":"init"},{"title":"Instance Properties","type":"groupMarker"},{"path":"\/documentation\/paywall\/experiment\/variant-swift.struct\/varianttype\/hashvalue","title":"var hashValue: Int","type":"property"},{"title":"Instance Methods","type":"groupMarker"},{"path":"\/documentation\/paywall\/experiment\/variant-swift.struct\/varianttype\/encode(to:)","title":"func encode(to: Encoder) throws","type":"method"},{"path":"\/documentation\/paywall\/experiment\/variant-swift.struct\/varianttype\/hash(into:)","title":"func hash(into: inout Hasher)","type":"method"}],"path":"\/documentation\/paywall\/experiment\/variant-swift.struct\/varianttype\/rawrepresentable-implementations","title":"RawRepresentable Implementations","type":"symbol"}],"path":"\/documentation\/paywall\/experiment\/variant-swift.struct\/varianttype","title":"Experiment.Variant.VariantType","type":"enum"},{"title":"Default Implementations","type":"groupMarker"},{"children":[{"title":"Operators","type":"groupMarker"},{"path":"\/documentation\/paywall\/experiment\/variant-swift.struct\/!=(_:_:)","title":"static func != (Self, Self) -> Bool","type":"op"}],"path":"\/documentation\/paywall\/experiment\/variant-swift.struct\/equatable-implementations","title":"Equatable Implementations","type":"symbol"}],"path":"\/documentation\/paywall\/experiment\/variant-swift.struct","title":"Experiment.Variant","type":"struct"},{"title":"Initializers","type":"groupMarker"},{"path":"\/documentation\/paywall\/experiment\/init(from:)","title":"init(from: Decoder) throws","type":"init"},{"title":"Instance Properties","type":"groupMarker"},{"path":"\/documentation\/paywall\/experiment\/groupid","title":"let groupId: String","type":"property"},{"path":"\/documentation\/paywall\/experiment\/id-swift.property","title":"let id: Experiment.ID","type":"property"},{"path":"\/documentation\/paywall\/experiment\/variant-swift.property","title":"let variant: Variant","type":"property"},{"title":"Instance Methods","type":"groupMarker"},{"path":"\/documentation\/paywall\/experiment\/encode(to:)","title":"func encode(to: Encoder) throws","type":"method"},{"title":"Type Aliases","type":"groupMarker"},{"path":"\/documentation\/paywall\/experiment\/id-swift.typealias","title":"Experiment.ID","type":"typealias"},{"title":"Default Implementations","type":"groupMarker"},{"children":[{"title":"Operators","type":"groupMarker"},{"path":"\/documentation\/paywall\/experiment\/!=(_:_:)","title":"static func != (Self, Self) -> Bool","type":"op"}],"path":"\/documentation\/paywall\/experiment\/equatable-implementations","title":"Equatable Implementations","type":"symbol"}],"path":"\/documentation\/paywall\/experiment","title":"Experiment","type":"struct"},{"children":[{"title":"Instance Properties","type":"groupMarker"},{"path":"\/documentation\/paywall\/paywalldismissalresult\/paywallinfo","title":"let paywallInfo: PaywallInfo?","type":"property"},{"path":"\/documentation\/paywall\/paywalldismissalresult\/state","title":"let state: DismissState","type":"property"},{"title":"Enumerations","type":"groupMarker"},{"children":[{"title":"Enumeration Cases","type":"groupMarker"},{"path":"\/documentation\/paywall\/paywalldismissalresult\/dismissstate\/closed","title":"case closed","type":"case"},{"path":"\/documentation\/paywall\/paywalldismissalresult\/dismissstate\/purchased(productid:)","title":"case purchased(productId: String)","type":"case"},{"path":"\/documentation\/paywall\/paywalldismissalresult\/dismissstate\/restored","title":"case restored","type":"case"}],"path":"\/documentation\/paywall\/paywalldismissalresult\/dismissstate","title":"PaywallDismissalResult.DismissState","type":"enum"}],"path":"\/documentation\/paywall\/paywalldismissalresult","title":"PaywallDismissalResult","type":"struct"},{"title":"Enumerations","type":"groupMarker"},{"children":[{"title":"Enumeration Cases","type":"groupMarker"},{"path":"\/documentation\/paywall\/loglevel\/debug","title":"case debug","type":"case"},{"path":"\/documentation\/paywall\/loglevel\/error","title":"case error","type":"case"},{"path":"\/documentation\/paywall\/loglevel\/info","title":"case info","type":"case"},{"path":"\/documentation\/paywall\/loglevel\/warn","title":"case warn","type":"case"},{"title":"Initializers","type":"groupMarker"},{"path":"\/documentation\/paywall\/loglevel\/init(rawvalue:)","title":"init?(rawValue: Int)","type":"init"},{"title":"Instance Properties","type":"groupMarker"},{"path":"\/documentation\/paywall\/loglevel\/description","title":"var description: String","type":"property"},{"title":"Default Implementations","type":"groupMarker"},{"children":[{"title":"Operators","type":"groupMarker"},{"path":"\/documentation\/paywall\/loglevel\/!=(_:_:)","title":"static func != (Self, Self) -> Bool","type":"op"}],"path":"\/documentation\/paywall\/loglevel\/equatable-implementations","title":"Equatable Implementations","type":"symbol"},{"children":[{"title":"Instance Properties","type":"groupMarker"},{"path":"\/documentation\/paywall\/loglevel\/hashvalue","title":"var hashValue: Int","type":"property"},{"title":"Instance Methods","type":"groupMarker"},{"path":"\/documentation\/paywall\/loglevel\/hash(into:)","title":"func hash(into: inout Hasher)","type":"method"}],"path":"\/documentation\/paywall\/loglevel\/rawrepresentable-implementations","title":"RawRepresentable Implementations","type":"symbol"}],"path":"\/documentation\/paywall\/loglevel","title":"LogLevel","type":"enum"},{"children":[{"title":"Enumeration Cases","type":"groupMarker"},{"path":"\/documentation\/paywall\/logscope\/all","title":"case all","type":"case"},{"path":"\/documentation\/paywall\/logscope\/bouncebutton","title":"case bounceButton","type":"case"},{"path":"\/documentation\/paywall\/logscope\/cache","title":"case cache","type":"case"},{"path":"\/documentation\/paywall\/logscope\/configmanager","title":"case configManager","type":"case"},{"path":"\/documentation\/paywall\/logscope\/coredata","title":"case coreData","type":"case"},{"path":"\/documentation\/paywall\/logscope\/debugmanager","title":"case debugManager","type":"case"},{"path":"\/documentation\/paywall\/logscope\/debugviewcontroller","title":"case debugViewController","type":"case"},{"path":"\/documentation\/paywall\/logscope\/device","title":"case device","type":"case"},{"path":"\/documentation\/paywall\/logscope\/events","title":"case events","type":"case"},{"path":"\/documentation\/paywall\/logscope\/gamecontrollermanager","title":"case gameControllerManager","type":"case"},{"path":"\/documentation\/paywall\/logscope\/localizationmanager","title":"case localizationManager","type":"case"},{"path":"\/documentation\/paywall\/logscope\/localizationviewcontroller","title":"case localizationViewController","type":"case"},{"path":"\/documentation\/paywall\/logscope\/network","title":"case network","type":"case"},{"path":"\/documentation\/paywall\/logscope\/paywallcore","title":"case paywallCore","type":"case"},{"path":"\/documentation\/paywall\/logscope\/paywallevents","title":"case paywallEvents","type":"case"},{"path":"\/documentation\/paywall\/logscope\/paywallpresentation","title":"case paywallPresentation","type":"case"},{"path":"\/documentation\/paywall\/logscope\/paywallresponsemanager","title":"case paywallResponseManager","type":"case"},{"path":"\/documentation\/paywall\/logscope\/paywalltransactions","title":"case paywallTransactions","type":"case"},{"path":"\/documentation\/paywall\/logscope\/paywallviewcontroller","title":"case paywallViewController","type":"case"},{"path":"\/documentation\/paywall\/logscope\/productsmanager","title":"case productsManager","type":"case"},{"path":"\/documentation\/paywall\/logscope\/storekitmanager","title":"case storeKitManager","type":"case"},{"title":"Initializers","type":"groupMarker"},{"path":"\/documentation\/paywall\/logscope\/init(rawvalue:)","title":"init?(rawValue: String)","type":"init"},{"title":"Default Implementations","type":"groupMarker"},{"children":[{"title":"Operators","type":"groupMarker"},{"path":"\/documentation\/paywall\/logscope\/!=(_:_:)","title":"static func != (Self, Self) -> Bool","type":"op"}],"path":"\/documentation\/paywall\/logscope\/equatable-implementations","title":"Equatable Implementations","type":"symbol"},{"children":[{"title":"Instance Properties","type":"groupMarker"},{"path":"\/documentation\/paywall\/logscope\/hashvalue","title":"var hashValue: Int","type":"property"},{"title":"Instance Methods","type":"groupMarker"},{"path":"\/documentation\/paywall\/logscope\/hash(into:)","title":"func hash(into: inout Hasher)","type":"method"}],"path":"\/documentation\/paywall\/logscope\/rawrepresentable-implementations","title":"RawRepresentable Implementations","type":"symbol"}],"path":"\/documentation\/paywall\/logscope","title":"LogScope","type":"enum"},{"children":[{"title":"Enumeration Cases","type":"groupMarker"},{"path":"\/documentation\/paywall\/paywallpresentationstyle\/fullscreen","title":"case fullscreen","type":"case"},{"path":"\/documentation\/paywall\/paywallpresentationstyle\/fullscreennoanimation","title":"case fullscreenNoAnimation","type":"case"},{"path":"\/documentation\/paywall\/paywallpresentationstyle\/modal","title":"case modal","type":"case"},{"path":"\/documentation\/paywall\/paywallpresentationstyle\/none","title":"case none","type":"case"},{"path":"\/documentation\/paywall\/paywallpresentationstyle\/push","title":"case push","type":"case"},{"title":"Initializers","type":"groupMarker"},{"path":"\/documentation\/paywall\/paywallpresentationstyle\/init(from:)-4er58","title":"init(from: Decoder) throws","type":"init"},{"path":"\/documentation\/paywall\/paywallpresentationstyle\/init(rawvalue:)","title":"init?(rawValue: Int)","type":"init"},{"title":"Default Implementations","type":"groupMarker"},{"children":[{"title":"Operators","type":"groupMarker"},{"path":"\/documentation\/paywall\/paywallpresentationstyle\/!=(_:_:)","title":"static func != (Self, Self) -> Bool","type":"op"}],"path":"\/documentation\/paywall\/paywallpresentationstyle\/equatable-implementations","title":"Equatable Implementations","type":"symbol"},{"children":[{"title":"Initializers","type":"groupMarker"},{"path":"\/documentation\/paywall\/paywallpresentationstyle\/init(from:)-7cc1t","title":"init(from: Decoder) throws","type":"init"},{"title":"Instance Properties","type":"groupMarker"},{"path":"\/documentation\/paywall\/paywallpresentationstyle\/hashvalue","title":"var hashValue: Int","type":"property"},{"title":"Instance Methods","type":"groupMarker"},{"path":"\/documentation\/paywall\/paywallpresentationstyle\/hash(into:)","title":"func hash(into: inout Hasher)","type":"method"}],"path":"\/documentation\/paywall\/paywallpresentationstyle\/rawrepresentable-implementations","title":"RawRepresentable Implementations","type":"symbol"}],"path":"\/documentation\/paywall\/paywallpresentationstyle","title":"PaywallPresentationStyle","type":"enum"}],"path":"\/documentation\/paywall","title":"Paywall","type":"module"}]},"schemaVersion":{"major":0,"minor":1,"patch":0}}